ultracompress_module/__init__.py
ultracompress_module/ultrajson_pro.py
ultracompress_module-0.3.3.dist-info/licenses/LICENSE.txt
ultracompress_module-0.3.3.dist-info/METADATA
ultracompress_module-0.3.3.dist-info/WHEEL
ultracompress_module-0.3.3.dist-info/entry_points.txt
ultracompress_module-0.3.3.dist-info/top_level.txt
ultracompress_module-0.3.3.dist-info/RECORD
