Metadata-Version: 2.4
Name: ultracompress_module
Version: 0.3.3
Summary: Multi-mode (fast/aggressive/ultra) JSON compressor with advanced reversible transform pipelines
Author: Béret
Author-email: admin@levraiberet.ovh
Requires-Python: >=3.8
License-File: LICENSE.txt
Requires-Dist: msgpack
Requires-Dist: zstandard
Requires-Dist: tqdm
Requires-Dist: ijson
Requires-Dist: base91
Requires-Dist: brotli
Dynamic: author
Dynamic: author-email
Dynamic: description
Dynamic: description-content-type
Dynamic: license-file
Dynamic: requires-dist
Dynamic: requires-python
Dynamic: summary
